pyck/__init__.py
pyck/__pycache__/__init__.cpython-310.pyc
pyck/controllers/__init__.py
pyck/controllers/crud_controller.py
pyck/ext/__init__.py
pyck/ext/admin_controller.py
pyck/forms/__init__.py
pyck/forms/form.py
pyck/forms/template_lookup.py
pyck/forms/templates/form_as_div.mako
pyck/forms/templates/form_as_p.mako
pyck/forms/templates/form_as_table.mako
pyck/lib/__init__.py
pyck/lib/color_logger.py
pyck/lib/dates_and_times.py
pyck/lib/models.py
pyck/lib/pagination.py
pyck/lib/pkg.py
pyck/lib/routes.py
pyck/lib/urls.py
pyck/mako_utils/__init__.py
pyck/mako_utils/multi_selector.py
pyck/mako_utils/template_lookup.py
pyck/mako_utils/templates/multi_selector.mako
pyck/scaffolds/__init__.py
pyck/scaffolds/template/CHANGES.txt
pyck/scaffolds/template/MANIFEST.in_tmpl
pyck/scaffolds/template/README.txt_tmpl
pyck/scaffolds/template/development.ini_tmpl
pyck/scaffolds/template/production.ini_tmpl
pyck/scaffolds/template/setup.cfg_tmpl
pyck/scaffolds/template/setup.py_tmpl
pyck/scaffolds/template/test.ini_tmpl
pyck/scaffolds/template/+package+/__init__.py_tmpl
pyck/scaffolds/template/+package+/auth.py
pyck/scaffolds/template/+package+/routes.py
pyck/scaffolds/template/+package+/apps/__init__.py_tmpl
pyck/scaffolds/template/+package+/controllers/__init__.py_tmpl
pyck/scaffolds/template/+package+/controllers/auth.py_tmpl
pyck/scaffolds/template/+package+/controllers/controllers.py_tmpl
pyck/scaffolds/template/+package+/forms/__init__.py
pyck/scaffolds/template/+package+/forms/auth.py
pyck/scaffolds/template/+package+/forms/contact.py
pyck/scaffolds/template/+package+/models/__init__.py_tmpl
pyck/scaffolds/template/+package+/models/auth.py_tmpl
pyck/scaffolds/template/+package+/models/models.py_tmpl
pyck/scaffolds/template/+package+/scripts/__init__.py_tmpl
pyck/scaffolds/template/+package+/scripts/newapp.py
pyck/scaffolds/template/+package+/scripts/newapp_scaffold.zip
pyck/scaffolds/template/+package+/scripts/populate.py_tmpl
PyCK-0.10.8.dist-info/LICENSE.txt
PyCK-0.10.8.dist-info/METADATA
PyCK-0.10.8.dist-info/WHEEL
PyCK-0.10.8.dist-info/entry_points.txt
PyCK-0.10.8.dist-info/top_level.txt
PyCK-0.10.8.dist-info/RECORD
