Metadata-Version: 2.1
Name: PyCK
Version: 0.10.8
Summary: Python Code Karigar - Web Framework
Home-page: http://pyck.compulife.com.pk
Author: Kashif Iftikhar
Author-email: kashif@compulife.com.pk
License: UNKNOWN
Keywords: web wsgi bfg pylons pyramid
Platform: UNKNOWN
Classifier: Programming Language :: Python
Classifier: Framework :: Pyramid
Classifier: Topic :: Internet :: WWW/HTTP
Classifier: Topic :: Internet :: WWW/HTTP :: WSGI :: Application
License-File: LICENSE.txt
Requires-Dist: SQLAlchemy (==1.4.46)
Requires-Dist: mako
Requires-Dist: nose
Requires-Dist: pyramid (==1.10.8)
Requires-Dist: pyramid-debugtoolbar
Requires-Dist: pyramid-mako
Requires-Dist: pyramid-tm
Requires-Dist: python-dateutil
Requires-Dist: transaction
Requires-Dist: wtdojo
Requires-Dist: wtforms
Requires-Dist: zope.sqlalchemy (==1.5)
